rotary_embedding_torch/__init__.py
rotary_embedding_torch/rotary_embedding_torch.py
rotary_embedding_torch-0.8.8.dist-info/licenses/LICENSE
rotary_embedding_torch-0.8.8.dist-info/METADATA
rotary_embedding_torch-0.8.8.dist-info/WHEEL
rotary_embedding_torch-0.8.8.dist-info/top_level.txt
rotary_embedding_torch-0.8.8.dist-info/RECORD
